shnu/__init__.py
shnu/shnuer-1.py
shnu/shnuer.py
shnu/tools.py
shnu_education_tools-26.1.18.dist-info/METADATA
shnu_education_tools-26.1.18.dist-info/WHEEL
shnu_education_tools-26.1.18.dist-info/entry_points.txt
shnu_education_tools-26.1.18.dist-info/top_level.txt
shnu_education_tools-26.1.18.dist-info/RECORD
