Metadata-Version: 2.4
Name: shnu-education-tools
Version: 26.1.18
Summary: SHNU education tools for teaching, grading, and automation
Home-page: https://github.com/liluqun
Author: Prof. Luqun Li
Author-email: liluqun@gmail.com
License: MIT
Project-URL: Source, https://github.com/liluqun/Shnu_Education_Tools
Project-URL: Bug Tracker, https://github.com/liluqun/Shnu_Education_Tools/issues
Keywords: education, teaching, grading, excel, pandas, openpyxl
Classifier: Programming Language :: Python :: 3
Classifier: Programming Language :: Python :: 3 :: Only
Classifier: Programming Language :: Python :: 3.9
Classifier: Programming Language :: Python :: 3.10
Classifier: Programming Language :: Python :: 3.11
Classifier: Programming Language :: Python :: 3.12
Classifier: License :: OSI Approved :: MIT License
Classifier: Operating System :: OS Independent
Requires-Python: >=3.9
Requires-Dist: numpy>=1.22
Requires-Dist: pandas>=2.1
Requires-Dist: openpyxl>=3.1
Requires-Dist: matplotlib>=3.7
Requires-Dist: jieba>=0.42
Requires-Dist: xlsxwriter>=3.1
Requires-Dist: requests>=2.31
Provides-Extra: viz
Requires-Dist: seaborn>=0.13; extra == "viz"
Provides-Extra: tts
Requires-Dist: pyttsx3>=2.90; extra == "tts"
Provides-Extra: audio
Requires-Dist: pydub>=0.25; extra == "audio"
